usdm4_cpt/__info__.py
usdm4_cpt/__init__.py
usdm4_cpt/document_view/__init__.py
usdm4_cpt/document_view/document_view.py
usdm4_cpt/import_/__init__.py
usdm4_cpt/import_/cpt_import.py
usdm4_cpt/import_/assemble/__init__.py
usdm4_cpt/import_/extract/__init__.py
usdm4_cpt/import_/extract/lab_tests.py
usdm4_cpt/import_/extract/soa.py
usdm4_cpt/import_/extract/title_page.py
usdm4_cpt/import_/extract/utility.py
usdm4_cpt/import_/extract/soa_features/__init__.py
usdm4_cpt/import_/extract/soa_features/activities_feature.py
usdm4_cpt/import_/extract/soa_features/activity_row_feature.py
usdm4_cpt/import_/extract/soa_features/conditions_feature.py
usdm4_cpt/import_/extract/soa_features/epochs_feature.py
usdm4_cpt/import_/extract/soa_features/expand_table.py
usdm4_cpt/import_/extract/soa_features/notes_feature.py
usdm4_cpt/import_/extract/soa_features/timepoints_feature.py
usdm4_cpt/import_/extract/soa_features/utility.py
usdm4_cpt/import_/extract/soa_features/visits_feature.py
usdm4_cpt/import_/extract/soa_features/windows_feature.py
usdm4_cpt/import_/load/__init__.py
usdm4_cpt/soa/__init__.py
usdm4_cpt/soa/soa.py
usdm4_cpt-0.5.0.dist-info/licenses/LICENSE
usdm4_cpt-0.5.0.dist-info/METADATA
usdm4_cpt-0.5.0.dist-info/WHEEL
usdm4_cpt-0.5.0.dist-info/top_level.txt
usdm4_cpt-0.5.0.dist-info/RECORD
