Metadata-Version: 2.4
Name: usdm4_cpt
Version: 0.5.0
Summary: A package for processing TransCelerate CPT protocol documents and converting them to USDM format
Author: D Iberson-Hurst
Author-email: 
Classifier: Intended Audience :: Developers
Classifier: Programming Language :: Python
Classifier: Programming Language :: Python :: 3
Classifier: Programming Language :: Python :: 3.12
Classifier: Operating System :: OS Independent
Requires-Python: >=3.12
License-File: LICENSE
Requires-Dist: usdm4>=0.14.0
Requires-Dist: raw_docx>=0.11.0
Dynamic: author
Dynamic: classifier
Dynamic: description
Dynamic: description-content-type
Dynamic: license-file
Dynamic: requires-dist
Dynamic: requires-python
Dynamic: summary
